rttlib/__init__.py
rttlib/api.py
rttlib/models.py
rttlib-0.1.0.dist-info/LICENSE.md
rttlib-0.1.0.dist-info/WHEEL
rttlib-0.1.0.dist-info/METADATA
rttlib-0.1.0.dist-info/RECORD
