Metadata-Version: 2.1
Name: rttlib
Version: 0.1.0
Summary: Wrapper for the RealTimeTrains API
Author: lyiriyah
Author-email: lyiriyah@tutanota.com
Requires-Python: >=3.10,<4.0
Classifier: Programming Language :: Python :: 3
Classifier: Programming Language :: Python :: 3.10
Classifier: Programming Language :: Python :: 3.11
Requires-Dist: pydantic (>=1.10.2,<2.0.0)
Requires-Dist: requests (>=2.28.1,<3.0.0)
